ncOrtho/__init__.py
ncOrtho/blastparser.py
ncOrtho/cmsearch.py
ncOrtho/genparser.py
ncOrtho/ncortho.py
ncOrtho/reblast.py
ncOrtho/rna_object.py
ncOrtho/utils.py
ncOrtho/analysis/__init__.py
ncOrtho/analysis/concat_alignments_dmp.pl
ncOrtho/analysis/degapper.pl
ncOrtho/analysis/ncAnalyze.py
ncOrtho/check/__init__.py
ncOrtho/check/core_synteny.py
ncOrtho/coreset/__init__.py
ncOrtho/coreset/core_reblast.py
ncOrtho/coreset/coreset.py
ncOrtho/coreset/coreset_utils.py
ncOrtho/coreset/createcm.py
ncOrtho/coreset/example_parameters.yaml
ncOrtho/coreset/locate_position.py
ncOrtho/coreset/synteny.py
ncortho-0.4.7.dist-info/LICENSE
ncortho-0.4.7.dist-info/METADATA
ncortho-0.4.7.dist-info/WHEEL
ncortho-0.4.7.dist-info/entry_points.txt
ncortho-0.4.7.dist-info/top_level.txt
ncortho-0.4.7.dist-info/RECORD
