Metadata-Version: 2.1
Name: ncOrtho
Version: 0.4.7
Summary: Targeted ortholog search for miRNAs 
Home-page: https://github.com/felixlangschied/ncortho
Author: Felix Langschied
Author-email: langschied@bio.uni-frankfurt.de
License: GPL-3.0
Classifier: Environment :: Console
Classifier: Intended Audience :: End Users/Desktop
Classifier: License :: OSI Approved :: GNU General Public License v3 or later (GPLv3+)
Classifier: Natural Language :: English
Classifier: Programming Language :: Python :: 3
Requires-Python: >=3.7.0
License-File: LICENSE
Requires-Dist: PyYAML
Requires-Dist: biopython
Requires-Dist: pyfaidx
Requires-Dist: pyfiglet
